{
  "vpnenabled":"true",
  "fixcountry":"no",
  "countryenabled":"false",
  "countries": [
    {
      "name": "Norway",
      "country": "no",
      "servers": "8"
    },
    {
      "name": "Germany",
      "country": "de",
      "servers": "66"
    },
    {
      "name": "Hong Kong",
      "country": "hk",
      "servers": "4"
    },
    {
      "name": "Russia",
      "country": "ru",
      "servers": "12"
    },
    {
      "name": "Bulgaria",
      "country": "bg",
      "servers": "3"
    },
    {
       "name": "Japan",
      "country": "jp",
      "servers": "6"
    },
    {
      "name": "Denmark",
      "country": "dk",
      "servers": "14"
    },
    {
      "name": "Ukraine",
      "country": "ua",
      "servers": "6"
    },
    {
      "name": "France",
      "country": "fr",
      "servers": "8"
    },
    {
      "name": "Brazil",
      "country": "br",
      "servers": "6"
    },
    {
      "name": "Sweden",
      "country": "se",
      "servers": "4"
    },
    {
      "name": "Singapore",
      "country": "sg",
      "servers": "36"
    },
    {
      "name": "United Kingdom",
      "country": "gb",
      "servers": "12"
    },
    {
      "name": "Ireland",
      "country": "ie",
      "servers": "8"
    },
    {
      "name": "United States",
      "country": "us",
      "servers": "78"
    },
    {
      "name": "Canada",
      "country": "ca",
      "servers": "10"
    },
    {
      "name": "Switzerland",
      "country": "ch",
      "servers": "6"
    },
    {
      "name": "Mexico",
      "country": "mx",
      "servers": "4"
    },
    {
      "name": "Italy",
      "country": "it",
      "servers": "8"
    },
    {
      "name": "Spain",
      "country": "es",
      "servers": "5"
    },
    {
      "name": "Australia",
      "country": "au",
      "servers": "4"
    },
    {
      "name": "Czechia",
      "country": "cz",
      "servers": "6"
    },
    {
      "name": "Romania",
      "country": "ro",
      "servers": "6"
    },
    {
      "name": "Turkey",
      "country": "tr",
      "servers": "6"
    },
    {
      "name": "Netherlands",
      "country": "nl",
      "servers": "27"
    }
  ]
}
